{
    "Samy Lamlih": {
        "id": "1915615",
        "class": "5th grade ",
        "age": "18",
        "finalgrade": "191962"
    },
    "Test test": {
        "id": "984",
        "class": "3eme",
        "age": "14",
        "finalgrade": "18"
    },
    "TesTSTt Test": {
        "id": "8923749",
        "class": "6eme",
        "age": "12",
        "finalgrade": "14"
    },
    "Loubna Rabia": {
        "id": "1234",
        "class": "3eme",
        "age": "15",
        "finalgrade": "19"
    }
}